smartboiler/__init__.py
smartboiler/boiler.py
smartboiler/controller.py
smartboiler/data_handler.py
smartboiler/event_checker.py
smartboiler/forecast.py
smartboiler/fotovoltaics.py
smartboiler/main.py
smartboiler/switch.py
smartboiler/time_handler.py
smartboiler-1.2.dist-info/METADATA
smartboiler-1.2.dist-info/WHEEL
smartboiler-1.2.dist-info/entry_points.txt
smartboiler-1.2.dist-info/top_level.txt
smartboiler-1.2.dist-info/RECORD
