Metadata-Version: 2.1
Name: smartboiler
Version: 1.2
Summary: Smart boiling of household
Home-page: https://github.com/grinwi/smartboiler
Author: Adam GRUNWALD
Author-email: grunwald.adam24@gmail.com
Keywords: energy,management,optimization,hass
Classifier: Development Status :: 5 - Production/Stable
Classifier: Intended Audience :: Developers
Classifier: Topic :: Software Development :: Build Tools
Classifier: License :: OSI Approved :: MIT License
Classifier: Programming Language :: Python :: 3.10
Classifier: Operating System :: OS Independent
Requires-Python: >=3.9, <=3.10
Requires-Dist: geopy
Requires-Dist: google-api-python-client
Requires-Dist: google-auth-httplib2
Requires-Dist: google-auth-oauthlib
Requires-Dist: haversine
Requires-Dist: h5py==3.10.0
Requires-Dist: influxdb==5.3.1
Requires-Dist: keras==2.15.0
Requires-Dist: matplotlib==3.5.1
Requires-Dist: numpy>=1.22.2
Requires-Dist: pandas>=1.4.1
Requires-Dist: pytz>=2021.1
Requires-Dist: requests>=2.25.1
Requires-Dist: skforecast>=0.10.1
Requires-Dist: wheel
